<?xml version="1.0" encoding="UTF-8"?>
<DOCUMENT>
  <BASE_ID>22801201</BASE_ID>
  <ColSuppl_16>intellectuelles</ColSuppl_16>
  <ColSuppl_17>supérieures</ColSuppl_17>
  <ColSuppl_18>Maitrise</ColSuppl_18>
  <ColSuppl_19>d'anglais</ColSuppl_19>
  <ColSuppl_20>en</ColSuppl_20>
  <ColSuppl_21>Civilisation</ColSuppl_21>
  <ColSuppl_22>américaine</ColSuppl_22>
  <ColSuppl_23>+</ColSuppl_23>
  <ColSuppl_24>CAPES</ColSuppl_24>
  <ColSuppl_25>d'anglais</ColSuppl_25>
  <ColSuppl_26>Professeur</ColSuppl_26>
  <ColSuppl_27>d'angalis</ColSuppl_27>
  <ColSuppl_28>dans</ColSuppl_28>
  <ColSuppl_29>un</ColSuppl_29>
  <ColSuppl_30>lycée</ColSuppl_30>
  <Commentaire>Niveau</Commentaire>
  <DATE_COLLECT>2024-03-13T16:48:26.000Z</DATE_COLLECT>
  <ETAT>100</ETAT>
  <ID>30</ID>
  <IDQES>dataset_complet/dataset_complet_000114.xml</IDQES>
  <INSEE>4</INSEE>
  <Plateforme_id>1000</Plateforme_id>
  <Profession>(Master)</Profession>
  <Unnamed_>et</Unnamed_>
  <age_loc>52</age_loc>
  <classe_nouv>30-60</classe_nouv>
  <content>ils étaient à &amp;Vernet toi tu étais à Paris hm et toi tu es née à Paris tu es née à Paris oui oui oui  les Hauts-de-Seine oui oui tranquille accueillies  et ta fille  avec Frabçois Truffaut avec François  Truffaut Philippe Garrel mais il a pas eu de prix il a pas eu de prix il travaille encore hein la guerre en quarante-quatre Barnaby non on regarde  non ouais ouais ouais ouais hm si euh  Mon Oncle Charlie oui hein comment ? oui Jacqueline Maillan sur Paris il revient le théâtre des Deux Anes les Guignols on achète les livres café turc oui on mangeait des salades grecques avec euh oui oui oui il a fait la Guerre du Viêtnam non ça ne t'intéresse pas et  ça fait partie de nos activités ça ouais non on a pas ouais à part déjà les courses déjà aller faire les courses ça prend du temps le temps d'y aller et d'attendre non non non on y est déjà allées mais on y est qui vous tu as été deux mois toi euh oui elle est rentrée en deux mille un elle est rentrée en en amorc septembre deux mille un puisque Sarah est née en avril elle doit avoir les deux puisqu'elle  a été ça fait quatre ? y en a au moins quatre déjà j'espère ouais oui ça amorc ça signifie quoi Lutèce ? si y a encore des macarons  oui on regarde la trois pour les actualités régionales FR trois vous regardez ? ouais le Sancerrois le  Sancerrois hm le Cher le Sancerrois où il a été voir euh François le le Berry euh oui mais c'est pas encore moi bah par amorc par exemple euh on va prendre un exemple parce que c'est plus simple avec un exemple j'ai ma tante qui a une leucémie et un on a un ami qui y a deux ans euh l'avait vu et quand il l'a vu en rentrant on était à Tours en rentrant sur Orléans en voiture il nous a dit elle est foutue ta belle-soeur elle est elle en a plus que pour deux ans oui et là euh les médecins euh lui donnent quelques amorc ouais c'est ce qui est en train d'arriver donc euh donc euh ouais euh non  non mais en même temps euh on se dit mais qu'il a une intuition euh ah ouais non  j'ai juste une question euh euh ça va durer encore combien de temps pour euh maman parce que c'est simplement parce que si ça doit durer encore mettons une heure je peux aller chercher des croquettes pour les chats et puis je reviens et amorc j'ai le temps d'accord OK OK oui si j'ai le temps attends je vais regarder si j'ai ma carte bleue parce que euh alors euh chez euh cinq minutes si y a pas de circulation pour aller amorc jusqu'à l'animalerie euh ensuite le café c'est juste à côté mais ça ça peut attendre lundi moi j'en bois pas tout ou mardi j'en n'ai pas pour très longtemps une petite demi-heure non c'est bon j'ai ma carte oui c'est fini déjà ? finalement beaucoup plus tard ? là ça fait plus d'une demi-heure  non c'est amorc mademoiselle NPERS non elle est quand même euh elle a quand même enseigné  non c'était madame NPERS qui disait ça au lieu de amorc je lui ai répondu elle disait j'y ai répond j'y ai amorc ouais mais après un présent bien c'est amorc j'y ai je lui ai répondu j'y ai répond enfin c'est un peu c'est un peu amorc avalé et puis euh  ouais oh non je crois pas je crois que euh le français fautif ça existe aussi hein  l'anglais le verlan c'est ta femme mais tu as pas le droit de la voir mais c'est à dire que souvent euh la façon dont ils réagissent enfin je vois parmi mes élèves je crois qu'ils se euh dès qu'on leur dit quelque chose ou qu'on leur fait un reproche parce que  ils bavardent ou ils travaillent pas euh ils ont l'impression que qu'on est plein de préjugés donc ils se sentent agressés sur d'autres domaines que ceux sur lesquels on on les reprend en fait par exemple on leur dit euh euh mettez-vous à travailler euh et cetera ou moi je sais que je fais attention au gaspillage d'énergie donc j'éteins euh l'électricité quand il fait jour et donc y en a non non je vois pas même quand ils n'ont pas de lunettes  et puis ils pourraient se rapprocher du tableau au lieu de dire je ne vois pas et je leur dis ils sont des gaspilleurs et que ça coûte cher ça coûte cher même au contribuable oui voi- oui elle y en a une qui commence à dire en arabe elle est en train de dire que les arabes ils payent pas l'impôt tu vois enfin donc euh je veux dire et puis bon c'est vrai que moi c'est plus facile de penser que je suis je amorc je pourrais être facho ou ou contre eux c'est parce que euh je crois qu'il y a des préjugés dans tous les sens et c'est  et c'est plus difficile d'être blond aux yeux bleus et d'être une femme quand on est face à eux que amorc déjà même si j'étais maghrébine ce serait un peu moins difficile parce que je pense que y aurait plus de solidarité en tout cas euh parce qu'y a une grande solidarité quand même entre  eux pas toujours et je je veux dire y en a qui ont des situations difficiles quand je regarde les fiches et que je vois des gamins mère au foyer père chômage je veux dire que et puis j'ai encore deux petits frères et deux petites soeurs donc ils sont cinq et et déjà se lever pour aller à l'école quand personne se lève dans la famille c'est amorc c'est difficile parce que personne se lève pour aller travailler donc euh pourquoi se lever à sept heures ? euh si y a pas d'adultes qui sont présents pour les aider pour les assister un peu parce que même s'ils ont euh quinze seize ou dix-sept ans y a des choses euh ils attendent un peu que maman le fasse le matin euh je veux dire si personne est réveillé c'est c'est pas des situations faciles s'ils ont des devoirs à faire s'ils doivent s'occuper du petit frère ou de la petite soeur quand ils rentrent c'est difficile de faire les devoirs donc y a quand même des situations euh euh amorc oui oui oui qui bon qui sont peut-être liées à la société qui sont liées à  je crois qu'il faut aussi que les familles les individus prennent leurs responsabilités y a aussi des situations familiales et individuelles je veux dire que  on peut pas toujours euh rejeter sur la société euh bon c'est sûr quand le père est au chômage y a la société qui qui est responsable parce qu'elle fournit de possibilité euh aux gens mais euh y a aussi des situations euh familiales en fait vous mettez dessus de l'ail et du persil il vole il vole la nourriture des petits lui ah je vois on est venu prendre des recettes non à l'espagnole on met des tomates euh du poivron ça y est c'est les petits qui mangent poulet à l'ananas c'est c'est chinois ça alors amorc il a il faisait aussi du poulet avec euh il faisait bien la cuisine lui on voit qu'il avait voyagé à l'étranger celui qui a en plus des visions euh il a fermé les portes ? NPERS ah oui c'est vrai il a fermé les portes oui c'est à moi maintenant ?</content>
  <en>et</en>
  <etudes>7</etudes>
  <filename>ESLO2_ENT_1021_XF20_52.txt</filename>
  <niveau_etude>Bac</niveau_etude>
  <niveau_etude_normalise>+</niveau_etude_normalise>
  <propres>Cadres</propres>
  <termes>plus</termes>
  <QES_Ambiguous>Vernet;Barnaby;Sarah</QES_Ambiguous>
  <QES_City>Paris;Orléans</QES_City>
  <QES_Coldconcept>Frabçois truffaut;Ouais ouais;Jacqueline maillan sur paris;Salades grecques;Orléans en voiture;Amorc ouais;Intuition euh;Question euh;Temps d'accord;Mademoiselle npers;Madame npers;Amorc avalé;Gaspillage d'énergie;Yeux bleus;Gamins mère;Situations faciles;Situations euh;Tomates euh</QES_Coldconcept>
  <QES_Company>Lutèce</QES_Company>
  <QES_CompanyTopic>Lutèce</QES_CompanyTopic>
  <QES_CompanyUncategorized>Lutèce</QES_CompanyUncategorized>
  <QES_Concept>Leucémie;Électricité;Situation difficile;Situation familiale</QES_Concept>
  <QES_ConceptCategorized>Leucémie;Électricité;Situation difficile</QES_ConceptCategorized>
  <QES_ConceptEnergy>Électricité</QES_ConceptEnergy>
  <QES_ConceptHealth>Leucémie</QES_ConceptHealth>
  <QES_ConceptRisk>Situation difficile</QES_ConceptRisk>
  <QES_ConceptTopic>Leucémie</QES_ConceptTopic>
  <QES_ConceptUncategorized>Situation familiale</QES_ConceptUncategorized>
  <QES_Coreference>François Truffaut Philippe;Jacqueline Maillan</QES_Coreference>
  <QES_Country>Vietnam</QES_Country>
  <QES_CountryTopicCode>FR;VN</QES_CountryTopicCode>
  <QES_Event>Guerre Du Viêtnam</QES_Event>
  <QES_EventTopic>Guerre Du Viêtnam</QES_EventTopic>
  <QES_Html>&lt;html&gt;&lt;head&gt;&lt;/head&gt;&lt;body&gt;ils étaient à &amp;amp:&lt;Relation&gt;&lt;Relation&gt;&lt;Relation&gt;&lt;Ambiguous&gt;Vernet&lt;/Ambiguous&gt; toi tu étais à &lt;Location&gt;Paris&lt;/Location&gt;&lt;/Relation&gt; hm et toi tu es née à &lt;Location&gt;Paris&lt;/Location&gt;&lt;/Relation&gt; tu es née à &lt;Location&gt;Paris&lt;/Location&gt;&lt;/Relation&gt; oui oui oui les &lt;Relation&gt;&lt;Relation&gt;&lt;Relation&gt;&lt;Location&gt;Hauts-de-Seine&lt;/Location&gt; oui oui &lt;Sentiment&gt;tranquille&lt;/Sentiment&gt;&lt;/Relation&gt; accueillies et ta fille avec &lt;Coldconcept&gt;&lt;UnknownPerson&gt;Frabçois Truffaut&lt;/UnknownPerson&gt;&lt;/Coldconcept&gt;&lt;/Relation&gt; avec &lt;Person&gt;François Truffaut Philippe&lt;/Person&gt;&lt;/Relation&gt; Garrel mais il a pas eu de prix il a pas eu de prix &lt;Coreference&gt;il&lt;/Coreference&gt; travaille encore hein la guerre en quarante-quatre &lt;Relation&gt;&lt;Relation&gt;&lt;Ambiguous&gt;Barnaby&lt;/Ambiguous&gt; non on &lt;SentimentUncategorized&gt;regarde non &lt;Coldconcept&gt;ouais ouais&lt;/Coldconcept&gt;&lt;/SentimentUncategorized&gt;&lt;/Relation&gt; ouais ouais hm si euh Mon &lt;Unknown&gt;Oncle Charlie&lt;/Unknown&gt;&lt;/Relation&gt; oui hein comment ? oui &lt;Person&gt;Jacqueline Maillan&lt;/Person&gt; sur &lt;Relation&gt;&lt;Location&gt;Paris&lt;/Location&gt; il revient le théâtre des Deux Anes les Guignols on achète les livres &lt;SentimentUncategorized&gt;café turc&lt;/SentimentUncategorized&gt; oui on mangeait des &lt;Coldconcept&gt;salades grecques&lt;/Coldconcept&gt;&lt;/Relation&gt; avec euh oui oui oui &lt;Coreference&gt;il&lt;/Coreference&gt; a fait la &lt;Relation&gt;&lt;Event&gt;&lt;EventTopic&gt;Guerre du &lt;Location&gt;Viêtnam&lt;/Location&gt;&lt;/EventTopic&gt;&lt;/Event&gt; non ça ne t&amp;apos:&lt;Sentiment&gt;intéresse&lt;/Sentiment&gt;&lt;/Relation&gt; pas et ça &lt;SentimentUncategorized&gt;fait partie&lt;/SentimentUncategorized&gt; de nos activités ça ouais non on a pas ouais à part déjà les courses déjà aller faire les courses ça prend du temps le temps d&amp;apos:y aller et d&amp;apos:attendre non non non on y est déjà allées mais on y est qui vous tu as été deux mois toi euh oui elle est rentrée en deux mille un elle est rentrée en en amorc septembre deux mille un puisque &lt;Ambiguous&gt;Sarah&lt;/Ambiguous&gt; est née en avril elle doit avoir les deux puisqu&amp;apos:elle a été ça fait quatre ? y en a au moins quatre déjà j&amp;apos:espère ouais oui ça amorc ça signifie quoi &lt;Company&gt;Lutèce&lt;/Company&gt; ? si y a encore des macarons oui on regarde la trois pour les actualités régionales FR trois vous regardez ? ouais le Sancerrois le Sancerrois hm le Cher le Sancerrois où il a été voir euh François le le Berry euh oui mais c&amp;apos:est pas encore moi bah par amorc par exemple euh on va prendre un exemple parce que c&amp;apos:&lt;SentimentUncategorized&gt;est plus simple&lt;/SentimentUncategorized&gt; avec un exemple j&amp;apos:ai ma tante qui a une &lt;Concept&gt;&lt;ConceptHealth&gt;leucémie&lt;/ConceptHealth&gt;&lt;/Concept&gt; et un on a un ami qui y a deux ans euh l&amp;apos:avait vu et quand il l&amp;apos:a vu en rentrant on était à Tours en rentrant sur &lt;Coldconcept&gt;&lt;Location&gt;Orléans&lt;/Location&gt; en voiture&lt;/Coldconcept&gt; il nous a dit elle est &lt;Sentiment&gt;foutue&lt;/Sentiment&gt; ta belle-soeur elle est elle en a plus que pour deux ans oui et là euh les &lt;JobTitle&gt;médecins&lt;/JobTitle&gt; euh lui donnent quelques &lt;Coldconcept&gt;amorc ouais&lt;/Coldconcept&gt; c&amp;apos:est ce qui est en train d&amp;apos:arriver donc euh donc euh ouais euh non non mais en même temps euh on se dit mais qu&amp;apos:il a une &lt;Coldconcept&gt;intuition euh&lt;/Coldconcept&gt; ah ouais non j&amp;apos:ai juste une &lt;Coldconcept&gt;question euh&lt;/Coldconcept&gt; euh &lt;Sentiment&gt;ça va&lt;/Sentiment&gt; durer encore combien de temps pour euh &lt;JobTitle&gt;maman&lt;/JobTitle&gt; parce que c&amp;apos:est simplement parce que si ça doit durer encore mettons une heure je peux aller chercher des croquettes pour les chats et puis je reviens et amorc j&amp;apos:ai le &lt;Coldconcept&gt;temps d&amp;apos:accord&lt;/Coldconcept&gt; &lt;Sentiment&gt;OK OK&lt;/Sentiment&gt; oui si j&amp;apos:ai le temps attends je vais regarder si j&amp;apos:ai ma carte bleue parce que euh alors euh chez euh cinq minutes si y a pas de circulation pour aller amorc jusqu&amp;apos:à l&amp;apos:animalerie euh ensuite le café c&amp;apos:est juste à côté mais ça ça peut attendre lundi moi j&amp;apos:en bois pas tout ou mardi j&amp;apos:en n&amp;apos:ai pas pour très longtemps une petite demi-heure non c&amp;apos:&lt;Sentiment&gt;est bon&lt;/Sentiment&gt; j&amp;apos:ai ma carte oui c&amp;apos:est fini déjà ? finalement beaucoup plus tard ? là ça fait plus d&amp;apos:une demi-heure non c&amp;apos:est amorc &lt;Coldconcept&gt;mademoiselle &lt;UnknownOrganization&gt;NPERS&lt;/UnknownOrganization&gt;&lt;/Coldconcept&gt; non elle est quand même euh elle a quand même &lt;JobTitle&gt;enseigné&lt;/JobTitle&gt; non c&amp;apos:&lt;SentimentUncategorized&gt;était &lt;Coldconcept&gt;madame &lt;Unknown&gt;NPERS&lt;/Unknown&gt;&lt;/Coldconcept&gt;&lt;/SentimentUncategorized&gt; qui disait ça au lieu de amorc je lui ai répondu elle disait j&amp;apos:y ai répond j&amp;apos:y ai amorc ouais mais après un présent bien c&amp;apos:&lt;SentimentUncategorized&gt;est amorc&lt;/SentimentUncategorized&gt; j&amp;apos:y ai je lui ai répondu j&amp;apos:y ai répond enfin c&amp;apos:est un peu c&amp;apos:&lt;SentimentUncategorized&gt;est un peu &lt;Coldconcept&gt;amorc avalé&lt;/Coldconcept&gt;&lt;/SentimentUncategorized&gt; et puis euh ouais oh non je crois pas je crois que euh le français fautif ça existe aussi hein l&amp;apos:anglais le verlan c&amp;apos:est ta femme mais tu as &lt;Sentiment&gt;pas le droit&lt;/Sentiment&gt; de la voir mais c&amp;apos:est à dire que souvent euh la façon dont ils réagissent enfin je vois parmi mes &lt;JobTitle&gt;élèves&lt;/JobTitle&gt; je crois qu&amp;apos:ils se euh dès qu&amp;apos:on leur dit quelque chose ou qu&amp;apos:on leur fait un reproche parce que ils bavardent ou ils travaillent pas euh ils ont l&amp;apos:impression que qu&amp;apos:on &lt;SentimentUncategorized&gt;est plein&lt;/SentimentUncategorized&gt; de préjugés donc ils se sentent &lt;Sentiment&gt;agressés&lt;/Sentiment&gt; sur d&amp;apos:autres domaines que ceux sur lesquels on on les reprend en fait par exemple on leur dit euh euh mettez-vous à travailler euh et cetera ou moi je sais que je &lt;SentimentUncategorized&gt;fais attention&lt;/SentimentUncategorized&gt; au &lt;Coldconcept&gt;&lt;Sentiment&gt;gaspillage&lt;/Sentiment&gt; d&amp;apos:énergie&lt;/Coldconcept&gt; donc j&amp;apos:éteins euh l&amp;apos:&lt;Concept&gt;&lt;ConceptEnergy&gt;électricité&lt;/ConceptEnergy&gt;&lt;/Concept&gt; quand il fait jour et donc y en a non non je vois pas même quand ils n&amp;apos:ont pas de lunettes et puis ils pourraient se rapprocher du tableau au lieu de dire je ne vois pas et je leur dis ils sont des gaspilleurs et que ça &lt;SentimentUncategorized&gt;coûte cher&lt;/SentimentUncategorized&gt; ça coûte cher même au contribuable oui voi- oui elle y en a une qui commence à dire en arabe elle est en train de dire que les arabes ils payent pas l&amp;apos:impôt tu vois enfin donc euh je veux dire et puis &lt;Sentiment&gt;bon&lt;/Sentiment&gt; c&amp;apos:&lt;SentimentUncategorized&gt;est vrai&lt;/SentimentUncategorized&gt; que moi c&amp;apos:est &lt;Sentiment&gt;plus facile&lt;/Sentiment&gt; de penser que je suis je amorc je &lt;SentimentUncategorized&gt;pourrais être facho&lt;/SentimentUncategorized&gt; ou ou contre eux c&amp;apos:est parce que euh je crois qu&amp;apos:il y a des préjugés dans tous les sens et c&amp;apos:est et c&amp;apos:est &lt;Sentiment&gt;plus difficile&lt;/Sentiment&gt; d&amp;apos:&lt;SentimentUncategorized&gt;être blond&lt;/SentimentUncategorized&gt; aux &lt;Coldconcept&gt;yeux bleus&lt;/Coldconcept&gt; et d&amp;apos:être &lt;Organonoff&gt;une femme&lt;/Organonoff&gt; quand on &lt;SentimentUncategorized&gt;est face&lt;/SentimentUncategorized&gt; à eux que amorc déjà même si j&amp;apos:&lt;SentimentUncategorized&gt;étais maghrébine&lt;/SentimentUncategorized&gt; ce serait &lt;Sentiment&gt;un peu moins difficile&lt;/Sentiment&gt; parce que je pense que y &lt;SentimentUncategorized&gt;aurait plus de solidarité&lt;/SentimentUncategorized&gt; en tout cas euh parce qu&amp;apos:y a une grande solidarité quand même entre eux pas toujours et je je veux dire y en a qui ont des &lt;Concept&gt;&lt;ConceptRisk&gt;situations &lt;Sentiment&gt;difficiles&lt;/Sentiment&gt;&lt;/ConceptRisk&gt;&lt;/Concept&gt; quand je regarde les fiches et que je vois des &lt;Coldconcept&gt;gamins mère&lt;/Coldconcept&gt; au foyer &lt;SentimentUncategorized&gt;père chômage&lt;/SentimentUncategorized&gt; je veux dire que et puis j&amp;apos:ai encore deux petits &lt;JobTitle&gt;frères&lt;/JobTitle&gt; et deux petites soeurs donc ils &lt;SentimentUncategorized&gt;sont cinq&lt;/SentimentUncategorized&gt; et et déjà se lever pour aller à l&amp;apos:école quand personne se lève dans la famille c&amp;apos:&lt;SentimentUncategorized&gt;est amorc&lt;/SentimentUncategorized&gt; c&amp;apos:est &lt;Sentiment&gt;difficile&lt;/Sentiment&gt; parce que personne se lève pour aller travailler donc euh pourquoi se lever à sept heures ? euh si y a pas d&amp;apos:adultes qui &lt;SentimentUncategorized&gt;sont présents&lt;/SentimentUncategorized&gt; pour les aider pour les assister un peu parce que même s&amp;apos:ils ont euh quinze seize ou dix-sept ans y a des choses euh ils attendent un peu que &lt;JobTitle&gt;maman&lt;/JobTitle&gt; le fasse le matin euh je veux dire si personne est réveillé c&amp;apos:est c&amp;apos:est pas des &lt;Coldconcept&gt;situations &lt;Sentiment&gt;faciles&lt;/Sentiment&gt;&lt;/Coldconcept&gt; s&amp;apos:ils ont des devoirs à faire s&amp;apos:ils doivent s&amp;apos:occuper du petit &lt;JobTitle&gt;frère&lt;/JobTitle&gt; ou de la petite soeur quand ils rentrent c&amp;apos:est &lt;Sentiment&gt;difficile&lt;/Sentiment&gt; de faire les devoirs donc y a quand même des &lt;Coldconcept&gt;situations euh&lt;/Coldconcept&gt; euh amorc oui oui oui qui &lt;Sentiment&gt;bon&lt;/Sentiment&gt; qui sont peut-être liées à la société qui sont liées à je crois qu&amp;apos:il faut aussi que les familles les individus prennent leurs responsabilités y a aussi des &lt;Concept&gt;situations familiales&lt;/Concept&gt; et individuelles je veux dire que on peut pas toujours euh rejeter sur la société euh &lt;Sentiment&gt;bon&lt;/Sentiment&gt; c&amp;apos:est &lt;Sentiment&gt;sûr&lt;/Sentiment&gt; quand le père est au chômage y a la société qui qui &lt;SentimentUncategorized&gt;est responsable&lt;/SentimentUncategorized&gt; parce qu&amp;apos:elle fournit de possibilité euh aux gens mais euh y a aussi des &lt;Coldconcept&gt;situations euh&lt;/Coldconcept&gt; familiales en fait vous mettez dessus de l&amp;apos:ail et du persil il vole il vole la nourriture des petits lui ah je vois on est venu prendre des recettes non à l&amp;apos:espagnole on met des &lt;Coldconcept&gt;tomates euh&lt;/Coldconcept&gt; du poivron ça y est c&amp;apos:est les petits qui &lt;SentimentUncategorized&gt;mangent poulet&lt;/SentimentUncategorized&gt; à l&amp;apos:ananas c&amp;apos:est c&amp;apos:&lt;SentimentUncategorized&gt;est chinois&lt;/SentimentUncategorized&gt; ça alors amorc il a il faisait aussi du poulet avec euh il faisait bien la cuisine lui on voit qu&amp;apos:il avait voyagé à l&amp;apos:étranger celui qui a en plus des visions euh il a &lt;Unlocalized&gt;fermé les portes&lt;/Unlocalized&gt; ? &lt;Relation&gt;&lt;UnknownOrganization&gt;NPERS&lt;/UnknownOrganization&gt; ah oui c&amp;apos:&lt;SentimentUncategorized&gt;est vrai&lt;/SentimentUncategorized&gt; il a &lt;Unlocalized&gt;fermé les portes&lt;/Unlocalized&gt;&lt;/Relation&gt; oui c&amp;apos:est à moi maintenant ?&lt;/body&gt;&lt;/html&gt;</QES_Html>
  <QES_JobTitle>Médecins;Maman;Enseigné;Élèves;Frères;Frère</QES_JobTitle>
  <QES_Location>Paris;Hauts De Seine;Vietnam;Orléans</QES_Location>
  <QES_LocationTopic>Paris;Hauts De Seine;Vietnam;Orléans</QES_LocationTopic>
  <QES_Organonoff>Une Femme</QES_Organonoff>
  <QES_Person>François Truffaut Philippe;Jacqueline Maillan</QES_Person>
  <QES_PersonTopic>François Truffaut Philippe;Jacqueline Maillan</QES_PersonTopic>
  <QES_PersonUncategorized>Jacqueline Maillan</QES_PersonUncategorized>
  <QES_Region>Hauts De Seine</QES_Region>
  <QES_Relation>Type|Unknown|Category|Être|Ontology|None|Keyword|toi tu étais à|Sentiment_Force|0|Confidence|0.8|Source_Type|Uppers|Source_Text|Vernet|Source_Text_Original|Vernet|Source_Topic|False|Source_Ontology|Rule|Source_Category|None|Source_Category_1|None|Destination_Type|Location|Destination_Text|Paris|Destination_Text_Original|Paris|Destination_Topic|True|Destination_Ontology|Qta|Destination_Category|None|Destination_Category_1|None|Text|Vernet toi tu étais à Paris|Sentence|ils étaient à &amp;Vernet toi tu étais à Paris hm et toi tu es née à Paris tu es née à Paris oui oui oui les Hauts-de-Seine oui oui tranquille accueillies et ta fille avec Frabçois Truffaut avec François Truffaut Philippe Garrel mais il a pas eu de prix il a pas eu de prix il travaille encore hein la guerre en quarante-quatre Barnaby non on regarde non ouais ouais ouais ouais hm si euh Mon Oncle Charlie oui hein comment ?|Location|Paris;Type|Unknown|Category|Naître|Ontology|None|Keyword|toi tu étais à Paris hm et toi tu es née à|Sentiment_Force|0|Confidence|0.27|Source_Type|Uppers|Source_Text|Vernet|Source_Text_Original|Vernet|Source_Topic|False|Source_Ontology|Rule|Source_Category|None|Source_Category_1|None|Destination_Type|Location|Destination_Text|Paris|Destination_Text_Original|Paris|Destination_Topic|True|Destination_Ontology|Qta|Destination_Category|None|Destination_Category_1|None|Text|Vernet toi tu étais à Paris hm et toi tu es née à Paris|Sentence|ils étaient à &amp;Vernet toi tu étais à Paris hm et toi tu es née à Paris tu es née à Paris oui oui oui les Hauts-de-Seine oui oui tranquille accueillies et ta fille avec Frabçois Truffaut avec François Truffaut Philippe Garrel mais il a pas eu de prix il a pas eu de prix il travaille encore hein la guerre en quarante-quatre Barnaby non on regarde non ouais ouais ouais ouais hm si euh Mon Oncle Charlie oui hein comment ?|Location|Paris;Type|Unknown|Category|Naître|Ontology|None|Keyword|toi tu étais à Paris hm et toi tu es née à Paris tu es née à|Sentiment_Force|0|Confidence|0.0|Source_Type|Uppers|Source_Text|Vernet|Source_Text_Original|Vernet|Source_Topic|False|Source_Ontology|Rule|Source_Category|None|Source_Category_1|None|Destination_Type|Location|Destination_Text|Paris|Destination_Text_Original|Paris|Destination_Topic|True|Destination_Ontology|Qta|Destination_Category|None|Destination_Category_1|None|Text|Vernet toi tu étais à Paris hm et toi tu es née à Paris tu es née à Paris|Sentence|ils étaient à &amp;Vernet toi tu étais à Paris hm et toi tu es née à Paris tu es née à Paris oui oui oui les Hauts-de-Seine oui oui tranquille accueillies et ta fille avec Frabçois Truffaut avec François Truffaut Philippe Garrel mais il a pas eu de prix il a pas eu de prix il travaille encore hein la guerre en quarante-quatre Barnaby non on regarde non ouais ouais ouais ouais hm si euh Mon Oncle Charlie oui hein comment ?|Location|Paris;Type|Unknown|Category|Naître|Ontology|None|Keyword|hm et toi tu es née à Paris tu es née à Paris oui oui oui les|Sentiment_Force|0|Confidence|0.0|Source_Type|Location|Source_Text|Paris|Source_Text_Original|Paris|Source_Topic|True|Source_Ontology|Qta|Source_Category|None|Source_Category_1|None|Destination_Type|Location|Destination_Text|Hauts De Seine|Destination_Text_Original|Hauts-De-Seine|Destination_Topic|True|Destination_Ontology|Qta|Destination_Category|None|Destination_Category_1|None|Text|Paris hm et toi tu es née à Paris tu es née à Paris oui oui oui les Hauts-de-Seine|Sentence|ils étaient à &amp;Vernet toi tu étais à Paris hm et toi tu es née à Paris tu es née à Paris oui oui oui les Hauts-de-Seine oui oui tranquille accueillies et ta fille avec Frabçois Truffaut avec François Truffaut Philippe Garrel mais il a pas eu de prix il a pas eu de prix il travaille encore hein la guerre en quarante-quatre Barnaby non on regarde non ouais ouais ouais ouais hm si euh Mon Oncle Charlie oui hein comment ?|Location|Paris;Type|Unknown|Category|Naître|Ontology|None|Keyword|tu es née à Paris oui oui oui les|Sentiment_Force|0|Confidence|0.47|Source_Type|Location|Source_Text|Paris|Source_Text_Original|Paris|Source_Topic|True|Source_Ontology|Qta|Source_Category|None|Source_Category_1|None|Destination_Type|Location|Destination_Text|Hauts De Seine|Destination_Text_Original|Hauts-De-Seine|Destination_Topic|True|Destination_Ontology|Qta|Destination_Category|None|Destination_Category_1|None|Text|Paris tu es née à Paris oui oui oui les Hauts-de-Seine|Sentence|ils étaient à &amp;Vernet toi tu étais à Paris hm et toi tu es née à Paris tu es née à Paris oui oui oui les Hauts-de-Seine oui oui tranquille accueillies et ta fille avec Frabçois Truffaut avec François Truffaut Philippe Garrel mais il a pas eu de prix il a pas eu de prix il travaille encore hein la guerre en quarante-quatre Barnaby non on regarde non ouais ouais ouais ouais hm si euh Mon Oncle Charlie oui hein comment ?|Location|Paris;Type|Sentiment|Category|Sentiment|Keyword|Tranquille|Sentiment_Force|1|Confidence|0.33|Between|ADV-ADV|Source_Type|Sentiment|Source_Text|Tranquille|Source_Text_Original|Tranquille|Source_Ontology|Qta|Source_Category|None|Source_Category_1|None|Destination_Type|Location|Destination_Text|Hauts De Seine|Destination_Text_Original|Hauts-De-Seine|Destination_Ontology|Qta|Destination_Category|None|Destination_Category_1|None|Text|Hauts-de-Seine oui oui tranquille|Sentence|ils étaient à &amp;Vernet toi tu étais à Paris hm et toi tu es née à Paris tu es née à Paris oui oui oui les Hauts-de-Seine oui oui tranquille accueillies et ta fille avec Frabçois Truffaut avec François Truffaut Philippe Garrel mais il a pas eu de prix il a pas eu de prix il travaille encore hein la guerre en quarante-quatre Barnaby non on regarde non ouais ouais ouais ouais hm si euh Mon Oncle Charlie oui hein comment ?;Type|Unknown|Category|Son|Ontology|None|Keyword|oui oui tranquille accueillies et ta fille avec|Sentiment_Force|0|Confidence|0.53|Source_Type|Location|Source_Text|Hauts De Seine|Source_Text_Original|Hauts-De-Seine|Source_Topic|True|Source_Ontology|Qta|Source_Category|None|Source_Category_1|None|Destination_Type|Coldconcept|Destination_Text|Frabçois Truffaut|Destination_Text_Original|Frabçois Truffaut|Destination_Topic|False|Destination_Ontology|Rule|Destination_Category|None|Destination_Category_1|None|Text|Hauts-de-Seine oui oui tranquille accueillies et ta fille avec Frabçois Truffaut|Sentence|ils étaient à &amp;Vernet toi tu étais à Paris hm et toi tu es née à Paris tu es née à Paris oui oui oui les Hauts-de-Seine oui oui tranquille accueillies et ta fille avec Frabçois Truffaut avec François Truffaut Philippe Garrel mais il a pas eu de prix il a pas eu de prix il travaille encore hein la guerre en quarante-quatre Barnaby non on regarde non ouais ouais ouais ouais hm si euh Mon Oncle Charlie oui hein comment ?|Location|Paris;Type|Unknown|Category|Son|Ontology|None|Keyword|oui oui tranquille accueillies et ta fille avec Frabçois Truffaut avec|Sentiment_Force|0|Confidence|0.33|Source_Type|Location|Source_Text|Hauts De Seine|Source_Text_Original|Hauts-De-Seine|Source_Topic|True|Source_Ontology|Qta|Source_Category|None|Source_Category_1|None|Destination_Type|Person|Destination_Text|François Truffaut Philippe|Destination_Text_Original|François Truffaut Philippe|Destination_Topic|True|Destination_Ontology|Rule|Destination_Category|None|Destination_Category_1|None|Text|Hauts-de-Seine oui oui tranquille accueillies et ta fille avec Frabçois Truffaut avec François Truffaut Philippe|Sentence|ils étaient à &amp;Vernet toi tu étais à Paris hm et toi tu es née à Paris tu es née à Paris oui oui oui les Hauts-de-Seine oui oui tranquille accueillies et ta fille avec Frabçois Truffaut avec François Truffaut Philippe Garrel mais il a pas eu de prix il a pas eu de prix il travaille encore hein la guerre en quarante-quatre Barnaby non on regarde non ouais ouais ouais ouais hm si euh Mon Oncle Charlie oui hein comment ?|Location|Paris;Type|Unknown|Category|Regarder|Ontology|None|Keyword|non on regarde non|Sentiment_Force|0|Confidence|0.8|Source_Type|Uppers|Source_Text|Barnaby|Source_Text_Original|Barnaby|Source_Topic|False|Source_Ontology|Rule|Source_Category|None|Source_Category_1|None|Destination_Type|Coldconcept|Destination_Text|Ouais Ouais|Destination_Text_Original|Ouais Ouais|Destination_Topic|False|Destination_Ontology|Rule|Destination_Category|None|Destination_Category_1|None|Text|Barnaby non on regarde non ouais ouais|Sentence|ils étaient à &amp;Vernet toi tu étais à Paris hm et toi tu es née à Paris tu es née à Paris oui oui oui les Hauts-de-Seine oui oui tranquille accueillies et ta fille avec Frabçois Truffaut avec François Truffaut Philippe Garrel mais il a pas eu de prix il a pas eu de prix il travaille encore hein la guerre en quarante-quatre Barnaby non on regarde non ouais ouais ouais ouais hm si euh Mon Oncle Charlie oui hein comment ?|Location|Paris;Type|Unknown|Category|Euh|Ontology|None|Keyword|non on regarde non ouais ouais ouais ouais hm si euh Mon|Sentiment_Force|0|Confidence|0.27|Source_Type|Uppers|Source_Text|Barnaby|Source_Text_Original|Barnaby|Source_Topic|False|Source_Ontology|Rule|Source_Category|None|Source_Category_1|None|Destination_Type|Uppers|Destination_Text|Oncle Charlie|Destination_Text_Original|Oncle Charlie|Destination_Topic|False|Destination_Ontology|Rule|Destination_Category|None|Destination_Category_1|None|Text|Barnaby non on regarde non ouais ouais ouais ouais hm si euh Mon Oncle Charlie|Sentence|ils étaient à &amp;Vernet toi tu étais à Paris hm et toi tu es née à Paris tu es née à Paris oui oui oui les Hauts-de-Seine oui oui tranquille accueillies et ta fille avec Frabçois Truffaut avec François Truffaut Philippe Garrel mais il a pas eu de prix il a pas eu de prix il travaille encore hein la guerre en quarante-quatre Barnaby non on regarde non ouais ouais ouais ouais hm si euh Mon Oncle Charlie oui hein comment ?|Location|Paris;Type|Unknown|Category|Acheter|Ontology|None|Keyword|il revient le théâtre des Deux Anes les Guignols on achète les livres café turc oui on mangeait des|Sentiment_Force|0|Confidence|0.0|Source_Type|Location|Source_Text|Paris|Source_Text_Original|Paris|Source_Topic|True|Source_Ontology|Qta|Source_Category|None|Source_Category_1|None|Destination_Type|Coldconcept|Destination_Text|Salades Grecques|Destination_Text_Original|Salades Grecques|Destination_Topic|False|Destination_Ontology|Rule|Destination_Category|None|Destination_Category_1|None|Text|Paris il revient le théâtre des Deux Anes les Guignols on achète les livres café turc oui on mangeait des salades grecques|Sentence|oui Jacqueline Maillan sur Paris il revient le théâtre des Deux Anes les Guignols on achète les livres café turc oui on mangeait des salades grecques avec euh oui oui oui il a fait la Guerre du Viêtnam non ça ne t'intéresse pas et ça fait partie de nos activités ça ouais non on a pas ouais à part déjà les courses déjà aller faire les courses ça prend du temps le temps d'y aller et d'attendre non non non on y est déjà allées mais on y est qui vous tu as été deux mois toi euh oui elle est rentrée |Number|Deux|Location|Paris;Type|Sentiment|Category|Sentiment|Keyword|Intéresse|Sentiment_Force|1|Confidence|0.0|Between|ADV-PRON-ADV-PRON|Source_Type|Sentiment|Source_Text|Intéresse|Source_Text_Original|Intéresse|Source_Ontology|Qta|Source_Category|None|Source_Category_1|None|Destination_Type|Event|Destination_Text|Guerre Du Viêtnam|Destination_Text_Original|Guerre Du Viêtnam|Destination_Ontology|Rule|Destination_Category|None|Destination_Category_1|None|Text|Guerre du Viêtnam non ça ne t'intéresse|Sentence|oui Jacqueline Maillan sur Paris il revient le théâtre des Deux Anes les Guignols on achète les livres café turc oui on mangeait des salades grecques avec euh oui oui oui il a fait la Guerre du Viêtnam non ça ne t'intéresse pas et ça fait partie de nos activités ça ouais non on a pas ouais à part déjà les courses déjà aller faire les courses ça prend du temps le temps d'y aller et d'attendre non non non on y est déjà allées mais on y est qui vous tu as été deux mois toi euh oui elle est rentrée ;Type|Sentiment|Category|Sentiment|Keyword|Intéresse|Sentiment_Force|1|Confidence|0.0|Between|ADV-PRON-ADV-PRON|Source_Type|Sentiment|Source_Text|Intéresse|Source_Text_Original|Intéresse|Source_Ontology|Qta|Source_Category|None|Source_Category_1|None|Destination_Type|Location|Destination_Text|Vietnam|Destination_Text_Original|Viêtnam|Destination_Ontology|Qta|Destination_Category|None|Destination_Category_1|None|Text|Viêtnam non ça ne t'intéresse|Sentence|oui Jacqueline Maillan sur Paris il revient le théâtre des Deux Anes les Guignols on achète les livres café turc oui on mangeait des salades grecques avec euh oui oui oui il a fait la Guerre du Viêtnam non ça ne t'intéresse pas et ça fait partie de nos activités ça ouais non on a pas ouais à part déjà les courses déjà aller faire les courses ça prend du temps le temps d'y aller et d'attendre non non non on y est déjà allées mais on y est qui vous tu as été deux mois toi euh oui elle est rentrée ;Type|Unknown|Category|Enseigner|Ontology|None|Keyword|non elle est quand même euh elle a quand même enseigné non c'était|Sentiment_Force|0|Confidence|0.13|Source_Type|Uppers|Source_Text|Npers|Source_Text_Original|Npers|Source_Topic|False|Source_Ontology|Rule|Source_Category|None|Source_Category_1|None|Destination_Type|Coldconcept|Destination_Text|Madame Npers|Destination_Text_Original|Madame Npers|Destination_Topic|False|Destination_Ontology|Rule|Destination_Category|None|Destination_Category_1|None|Text|NPERS non elle est quand même euh elle a quand même enseigné non c'était madame NPERS|Sentence|là ça fait plus d'une demi-heure non c'est amorc mademoiselle NPERS non elle est quand même euh elle a quand même enseigné non c'était madame NPERS qui disait ça au lieu de amorc je lui ai répondu elle disait j'y ai répond j'y ai amorc ouais mais après un présent bien c'est amorc j'y ai je lui ai répondu j'y ai répond enfin c'est un peu c'est un peu amorc avalé et puis euh ouais oh non je crois pas je crois que euh le français fautif ça existe aussi hein l'anglais le verlan c'est ta femme mais t;Type|Unknown|Category|Avoir|Ontology|None|Keyword|ah oui c'est vrai il a|Sentiment_Force|0|Confidence|0.6|Source_Type|Uppers|Source_Text|Npers|Source_Text_Original|Npers|Source_Topic|False|Source_Ontology|Rule|Source_Category|None|Source_Category_1|None|Destination_Type|Unlocalized|Destination_Text|Fermé Les Portes|Destination_Text_Original|Fermé Les Portes|Destination_Topic|False|Destination_Ontology|Rule|Destination_Category|None|Destination_Category_1|None|Text|NPERS ah oui c'est vrai il a fermé les portes|Sentence|NPERS ah oui c'est vrai il a fermé les portes oui c'est à moi maintenant ?</QES_Relation>
  <QES_Sentiment>Tranquille;Intéresse;Foutue;Ca Va;Ok ok;Est Bon;Pas Le Droit;Agressés;Gaspillage;Bon;Plus facile;Plus difficile;Un peu moins difficile;Difficiles;Difficile;Faciles;Sûr</QES_Sentiment>
  <QES_SentimentForce>0</QES_SentimentForce>
  <QES_SentimentUncategorized>Regarde Non Ouais Ouais;Euh Mon Oncle;Café Turc;Fait Partie;Est Plus Simple;Était Madame Npers;Est Amorc;Est Un Peu Amorc Avalé;Est Plein;Fais Attention;Coûte Cher;Est Vrai;Pourrais Être Facho;Être Blond;Est Face;Étais Maghrébine;Aurait Plus De Solidarité;Père Chômage;Sont Cinq;Sont Présents;Est Responsable;Mangent Poulet;Est Chinois</QES_SentimentUncategorized>
  <QES_Spatial>48.856944444,2.351388888;14.016666666667,107.9;47.902222222,1.904166666</QES_Spatial>
  <QES_Unknown>Oncle Charlie;Npers</QES_Unknown>
  <QES_UnknownOrganization>Npers</QES_UnknownOrganization>
  <QES_UnknownPerson>Frabçois Truffaut</QES_UnknownPerson>
  <QES_Unlocalized>Fermé Les Portes</QES_Unlocalized>
  <QES_Version>4079</QES_Version>
</DOCUMENT>